mailrobot/__init__.py
mailrobot/admin.py
mailrobot/models.py
mailrobot/migrations/0001_initial.py
mailrobot/migrations/__init__.py
django_mailrobot-0.8.1.dist-info/METADATA
django_mailrobot-0.8.1.dist-info/WHEEL
django_mailrobot-0.8.1.dist-info/licenses/LICENSE
django_mailrobot-0.8.1.dist-info/RECORD
